szpt_course_base/ClassQuery.py
szpt_course_base/__init__.py
szpt_course_option/CourseOption.py
szpt_course_option/__init__.py
szpt_course_option/verifyCode.py
szpt_course_reptile-0.0.5.dist-info/METADATA
szpt_course_reptile-0.0.5.dist-info/WHEEL
szpt_course_reptile-0.0.5.dist-info/top_level.txt
szpt_course_reptile-0.0.5.dist-info/RECORD
