Metadata-Version: 2.1
Name: szpt-course-reptile
Version: 0.0.5
Summary: use for get szpt course and option course
Home-page: https://github.com/pypa/sampleproject
Author: Cheney
Author-email: cheney2001@qq.com
License: UNKNOWN
Platform: UNKNOWN
Classifier: Programming Language :: Python :: 3
Classifier: License :: OSI Approved :: MIT License
Classifier: Operating System :: OS Independent
Requires-Python: >=3.6
Requires-Dist: requests (==2.24.0)
Requires-Dist: lxml (==4.6.1)
Requires-Dist: numpy (==1.19.4)
Requires-Dist: selenium (==3.141.0)
